label_tree/__init__.py
label_tree/diseases_tree.py
label_tree/exceptions.py
label_tree/utils.py
label_tree-1.0.5.dist-info/LICENSE.txt
label_tree-1.0.5.dist-info/METADATA
label_tree-1.0.5.dist-info/WHEEL
label_tree-1.0.5.dist-info/top_level.txt
label_tree-1.0.5.dist-info/RECORD
