Metadata-Version: 2.1
Name: label-tree
Version: 1.0.5
Summary: A minimal client to access the label tree across BeatBoxAI applications.
Home-page: https://github.com/Medpic/label-tree
Author: Noam Keidar
Author-email: noamkeidar@campus.technion.ac.il
License: MIT
Platform: any
Classifier: Development Status :: 5 - Production/Stable
Classifier: Programming Language :: Python
License-File: LICENSE.txt
Requires-Dist: pyyaml
Requires-Dist: igraph
Requires-Dist: boto3
Requires-Dist: python-dotenv
Requires-Dist: packaging
Requires-Dist: importlib-metadata ; python_version < "3.8"
Provides-Extra: dev
Requires-Dist: pre-commit ; extra == 'dev'
Provides-Extra: testing
Requires-Dist: setuptools ; extra == 'testing'
Requires-Dist: pytest ; extra == 'testing'
Requires-Dist: pyodbc ; extra == 'testing'
Provides-Extra: viz
Requires-Dist: pycairo ; extra == 'viz'
